tethysio/__init__.py
tethysio/scraper.py
tethysio-0.0.4.dist-info/METADATA
tethysio-0.0.4.dist-info/WHEEL
tethysio-0.0.4.dist-info/top_level.txt
tethysio-0.0.4.dist-info/RECORD
