Metadata-Version: 2.1
Name: tethysio
Version: 0.0.4
Summary: Scrape rec.gov permits
Home-page: https://github.com/rmcsqrd/tethys/tree/main/scraper
Author: Rio McMahon
Author-email: rmcsqrd@gmail.com
License: MIT
Platform: UNKNOWN
Classifier: License :: OSI Approved :: MIT License
Classifier: Programming Language :: Python
Classifier: Programming Language :: Python :: 3
Classifier: Programming Language :: Python :: 3.9
Requires-Python: >=3.9.0
Requires-Dist: BeautifulSoup4
Requires-Dist: requests
Requires-Dist: pandas
